{"chunk_definitions":[{"row":33,"row_count":1,"visible":true,"expansion_state":0,"options":{"engine":"r","label":"setup","include":false,"message":false},"document_id":"A6A437F2","chunk_id":"csetup_chunk","chunk_label":"setup"},{"row":60,"row_count":1,"visible":true,"expansion_state":0,"options":{"include":false,"engine":"r","label":"setup bc r is mad at me"},"document_id":"A6A437F2","chunk_id":"caikl1rf0bmul","chunk_label":"setup bc r is mad at me"},{"row":172,"row_count":1,"visible":true,"expansion_state":0,"options":{"engine":"r","echo":false,"warning":false,"message":false,"show_col_types":false,"label":"unnamed-chunk-66"},"document_id":"A6A437F2","chunk_id":"cjkeandln2k2n","chunk_label":"unnamed-chunk-1"},{"row":205,"row_count":1,"visible":true,"expansion_state":0,"options":{"engine":"r","message":false,"show_col_types":false,"label":"unnamed-chunk-21"},"document_id":"A6A437F2","chunk_id":"coib442l0ol28","chunk_label":"unnamed-chunk-2"},{"row":252,"row_count":1,"visible":true,"expansion_state":0,"options":{"engine":"r","echo":false,"label":"unnamed-chunk-20"},"document_id":"A6A437F2","chunk_id":"clpr42zmiel7e","chunk_label":"unnamed-chunk-3"},{"row":268,"row_count":1,"visible":true,"expansion_state":0,"options":{"engine":"r","label":"unnamed-chunk-97"},"document_id":"9C4BB16E","chunk_id":"ccaa5vb0avw3h","chunk_label":"unnamed-chunk-4"}],"doc_write_time":1665469143,"working_dir":null,"default_chunk_options":{}}